codesurvey/__init__.py
codesurvey/analyzers/__init__.py
codesurvey/analyzers/core.py
codesurvey/analyzers/features.py
codesurvey/analyzers/python/__init__.py
codesurvey/analyzers/python/core.py
codesurvey/analyzers/python/features.py
codesurvey/core.py
codesurvey/database.py
codesurvey/sources/__init__.py
codesurvey/sources/core.py
codesurvey/utils.py
codesurvey-0.1.5.dist-info/LICENSE
codesurvey-0.1.5.dist-info/METADATA
codesurvey-0.1.5.dist-info/WHEEL
codesurvey-0.1.5.dist-info/RECORD
