Metadata-Version: 2.1
Name: codesurvey
Version: 0.1.5
Summary: Analyse source code repositories for language feature and library usage.
Home-page: https://github.com/lean-python-org/codesurvey
License: GPL-3.0-only
Author: Ben Denham
Author-email: ben@denham.nz
Requires-Python: >=3.8,<4.0
Classifier: Development Status :: 2 - Pre-Alpha
Classifier: Intended Audience :: Developers
Classifier: Intended Audience :: Science/Research
Classifier: License :: OSI Approved :: GNU General Public License v3 (GPLv3)
Classifier: License :: OSI Approved :: MIT License
Classifier: Programming Language :: Python :: 3
Classifier: Programming Language :: Python :: 3.8
Classifier: Programming Language :: Python :: 3.9
Classifier: Programming Language :: Python :: 3.10
Classifier: Programming Language :: Python :: 3.11
Classifier: Programming Language :: Python :: 3.12
Classifier: Topic :: Scientific/Engineering :: Information Analysis
Classifier: Topic :: Software Development :: Libraries :: Python Modules
Requires-Dist: astpath (>=0.9.0,<0.10.0)
Requires-Dist: lxml (>=4.9.1,<5.0.0)
Requires-Dist: peewee (>=3.15.2,<4.0.0)
Requires-Dist: requests (>=2.28.1,<3.0.0)
Requires-Dist: tqdm (>=4.64.0,<5.0.0)
Project-URL: Repository, https://github.com/lean-python-org/codesurvey
